chipperchicken/__init__.py
chipperchicken/main.py
chipper_chicken-0.0.3.dist-info/LICENSE
chipper_chicken-0.0.3.dist-info/METADATA
chipper_chicken-0.0.3.dist-info/WHEEL
chipper_chicken-0.0.3.dist-info/top_level.txt
chipper_chicken-0.0.3.dist-info/RECORD
