Metadata-Version: 2.1
Name: chipper-chicken
Version: 0.0.3
Summary: Cryptography chipper for python
Home-page: https://github.com/Madhava-mng/Chipper-chicken
Author: Madhava-mng
Author-email: alformint@gmail.com
License: UNKNOWN
Platform: UNKNOWN
Classifier: Programming Language :: Python :: 3
Classifier: License :: OSI Approved :: MIT License
Classifier: Operating System :: OS Independent
Requires-Python: >=3.6
Requires-Dist: codelib
